aegir/__init__.py
aegir/_registry.py
aegir/constructors.py
aegir/entry.py
aegir/exceptions.py
aegir/file.py
aegir-1.0.2.dist-info/LICENSE
aegir-1.0.2.dist-info/WHEEL
aegir-1.0.2.dist-info/METADATA
aegir-1.0.2.dist-info/RECORD
