Metadata-Version: 2.1
Name: aegir
Version: 1.0.2
Summary: A minimal package to support configuration files without any additional work.
Home-page: https://github.com/akarys42/aegir
Author: Amber Bertucci
Author-email: amber@akarys.me
Requires-Python: >=3.8
Classifier: Development Status :: 5 - Production/Stable
Classifier: License :: OSI Approved :: MIT License
Classifier: Operating System :: OS Independent
Classifier: Programming Language :: Python
Classifier: Programming Language :: Python :: 3.8
Classifier: Programming Language :: Python :: 3.9
Classifier: Programming Language :: Python :: 3.10
Classifier: Topic :: Software Development :: Libraries :: Python Modules
Requires-Dist: PyYAML ~= 5.3
Requires-Dist: flake8 ~= 3.8 ; extra == "dev"
Requires-Dist: flake8-annotations ~= 2.0 ; extra == "dev"
Requires-Dist: flake8-bugbear ~= 20.1 ; extra == "dev"
Requires-Dist: flake8-docstrings ~= 1.4 ; extra == "dev"
Requires-Dist: flake8-import-order ~= 0.18 ; extra == "dev"
Requires-Dist: flake8-string-format ~= 0.2 ; extra == "dev"
Requires-Dist: flake8-tidy-imports ~= 4.0 ; extra == "dev"
Requires-Dist: flake8-todo ~= 0.7 ; extra == "dev"
Requires-Dist: pep8-naming ~= 0.9 ; extra == "dev"
Requires-Dist: black ~= 22.1 ; extra == "dev"
Provides-Extra: dev
